setup.cfg
setup.py
fileoperations/__init__.py
fileoperations/fileoperations.py
fileoperations_python.egg-info/PKG-INFO
fileoperations_python.egg-info/SOURCES.txt
fileoperations_python.egg-info/dependency_links.txt
fileoperations_python.egg-info/pbr.json
fileoperations_python.egg-info/top_level.txt