Metadata-Version: 1.0
Name: fileoperations-python
Version: 0.1
Summary: Basic I/O stuff for python
Home-page: https://github.com/sertansenturk/fileoperations_python
Author: Sertan Senturk
Author-email: contact@sertansenturk.com
License: UNKNOWN
Platform: UNKNOWN
